[
  {
    "id": "3uy0lik",
    "title": "Technical analysis: MSFT breakout incoming",
    "author": "user_5475",
    "subreddit": "stocks",
    "score": 2423,
    "num_comments": 263,
    "created_utc": 1784423256.1193738,
    "url": "https://reddit.com/r/stocks/",
    "timestamp": "2026-07-19T09:10:04.119757+00:00",
    "selftext": "Demo analysis for MSFT. This is fallback data - click to visit r/stocks.",
    "upvote_ratio": 0.9127763047399641,
    "over_18": false,
    "stickied": false,
    "comments": 110
  },
  {
    "id": "w31apth",
    "title": "Bought 1000 shares of GME - YOLO",
    "author": "user_9357",
    "subreddit": "wallstreetbets",
    "score": 2401,
    "num_comments": 133,
    "created_utc": 1784426765.1193738,
    "url": "https://reddit.com/r/wallstreetbets/",
    "timestamp": "2026-07-19T09:10:04.119854+00:00",
    "selftext": "Demo analysis for GME. This is fallback data - click to visit r/wallstreetbets.",
    "upvote_ratio": 0.861421051688709,
    "over_18": false,
    "stickied": false,
    "comments": 160
  },
  {
    "id": "q9djbfh",
    "title": "Technical analysis: SPY breakout incoming",
    "author": "user_8132",
    "subreddit": "stocks",
    "score": 2392,
    "num_comments": 239,
    "created_utc": 1784432152.1193738,
    "url": "https://reddit.com/r/stocks/",
    "timestamp": "2026-07-19T09:10:04.119685+00:00",
    "selftext": "Demo analysis for SPY. This is fallback data - click to visit r/stocks.",
    "upvote_ratio": 0.7572152064227198,
    "over_18": false,
    "stickied": false,
    "comments": 270
  },
  {
    "id": "vc8jljl",
    "title": "Hold or sell TSLA? Need advice",
    "author": "user_4240",
    "subreddit": "wallstreetbets",
    "score": 2290,
    "num_comments": 25,
    "created_utc": 1784415301.1193738,
    "url": "https://reddit.com/r/wallstreetbets/",
    "timestamp": "2026-07-19T09:10:04.119791+00:00",
    "selftext": "Demo analysis for TSLA. This is fallback data - click to visit r/wallstreetbets.",
    "upvote_ratio": 0.8586457954383517,
    "over_18": false,
    "stickied": false,
    "comments": 137
  },
  {
    "id": "oy28ae4",
    "title": "My AMZN position is printing \ud83d\udcb0",
    "author": "user_2503",
    "subreddit": "stocks",
    "score": 2128,
    "num_comments": 164,
    "created_utc": 1784439810.1193738,
    "url": "https://reddit.com/r/stocks/",
    "timestamp": "2026-07-19T09:10:04.119722+00:00",
    "selftext": "Demo analysis for AMZN. This is fallback data - click to visit r/stocks.",
    "upvote_ratio": 0.8379749449891288,
    "over_18": false,
    "stickied": false,
    "comments": 147
  },
  {
    "id": "vii8rd4",
    "title": "GME news catalyst could spark rally",
    "author": "user_9804",
    "subreddit": "investing",
    "score": 1639,
    "num_comments": 231,
    "created_utc": 1784433713.1193738,
    "url": "https://reddit.com/r/investing/",
    "timestamp": "2026-07-19T09:10:04.119560+00:00",
    "selftext": "Demo analysis for GME. This is fallback data - click to visit r/investing.",
    "upvote_ratio": 0.8095542094707784,
    "over_18": false,
    "stickied": false,
    "comments": 240
  },
  {
    "id": "di1k2m5",
    "title": "\ud83d\ude80 AMC to the moon! DD inside",
    "author": "user_1867",
    "subreddit": "stocks",
    "score": 1630,
    "num_comments": 133,
    "created_utc": 1784421342.1193738,
    "url": "https://reddit.com/r/stocks/",
    "timestamp": "2026-07-19T09:10:04.119614+00:00",
    "selftext": "Demo analysis for AMC. This is fallback data - click to visit r/stocks.",
    "upvote_ratio": 0.7964065097063984,
    "over_18": false,
    "stickied": false,
    "comments": 35
  },
  {
    "id": "b2hgzs0",
    "title": "Hold or sell TSLA? Need advice",
    "author": "user_5304",
    "subreddit": "stocks",
    "score": 1512,
    "num_comments": 202,
    "created_utc": 1784443558.1193738,
    "url": "https://reddit.com/r/stocks/",
    "timestamp": "2026-07-19T09:10:04.119578+00:00",
    "selftext": "Demo analysis for TSLA. This is fallback data - click to visit r/stocks.",
    "upvote_ratio": 0.7357555526677119,
    "over_18": false,
    "stickied": false,
    "comments": 290
  },
  {
    "id": "48jhm5c",
    "title": "NVDA short squeeze potential?",
    "author": "user_7634",
    "subreddit": "stocks",
    "score": 1483,
    "num_comments": 283,
    "created_utc": 1784434223.1193738,
    "url": "https://reddit.com/r/stocks/",
    "timestamp": "2026-07-19T09:10:04.119865+00:00",
    "selftext": "Demo analysis for NVDA. This is fallback data - click to visit r/stocks.",
    "upvote_ratio": 0.8908409280179006,
    "over_18": false,
    "stickied": false,
    "comments": 148
  },
  {
    "id": "u1tmt1c",
    "title": "GME dip - perfect entry point?",
    "author": "user_2224",
    "subreddit": "stocks",
    "score": 1454,
    "num_comments": 295,
    "created_utc": 1784452032.1193738,
    "url": "https://reddit.com/r/stocks/",
    "timestamp": "2026-07-19T09:10:04.119541+00:00",
    "selftext": "Demo analysis for GME. This is fallback data - click to visit r/stocks.",
    "upvote_ratio": 0.9018061211673118,
    "over_18": false,
    "stickied": false,
    "comments": 181
  },
  {
    "id": "p94fppm",
    "title": "Bought 1000 shares of AAPL - YOLO",
    "author": "user_8424",
    "subreddit": "stocks",
    "score": 1413,
    "num_comments": 161,
    "created_utc": 1784427888.1193738,
    "url": "https://reddit.com/r/stocks/",
    "timestamp": "2026-07-19T09:10:04.119594+00:00",
    "selftext": "Demo analysis for AAPL. This is fallback data - click to visit r/stocks.",
    "upvote_ratio": 0.792915684762372,
    "over_18": false,
    "stickied": false,
    "comments": 67
  },
  {
    "id": "mf89eg9",
    "title": "Bought 1000 shares of GME - YOLO",
    "author": "user_7865",
    "subreddit": "stocks",
    "score": 1347,
    "num_comments": 185,
    "created_utc": 1784410559.1193738,
    "url": "https://reddit.com/r/stocks/",
    "timestamp": "2026-07-19T09:10:04.119633+00:00",
    "selftext": "Demo analysis for GME. This is fallback data - click to visit r/stocks.",
    "upvote_ratio": 0.7032533401299279,
    "over_18": false,
    "stickied": false,
    "comments": 139
  },
  {
    "id": "lzkcuwh",
    "title": "GME news catalyst could spark rally",
    "author": "user_1892",
    "subreddit": "investing",
    "score": 1346,
    "num_comments": 80,
    "created_utc": 1784439605.1193738,
    "url": "https://reddit.com/r/investing/",
    "timestamp": "2026-07-19T09:10:04.119523+00:00",
    "selftext": "Demo analysis for GME. This is fallback data - click to visit r/investing.",
    "upvote_ratio": 0.7245492355551251,
    "over_18": false,
    "stickied": false,
    "comments": 116
  },
  {
    "id": "dvaura1",
    "title": "Why MSFT is the play of the decade",
    "author": "user_1560",
    "subreddit": "stocks",
    "score": 1273,
    "num_comments": 104,
    "created_utc": 1784424687.1193738,
    "url": "https://reddit.com/r/stocks/",
    "timestamp": "2026-07-19T09:10:04.119740+00:00",
    "selftext": "Demo analysis for MSFT. This is fallback data - click to visit r/stocks.",
    "upvote_ratio": 0.8639306727331245,
    "over_18": false,
    "stickied": false,
    "comments": 276
  },
  {
    "id": "7nmg0h1",
    "title": "TSLA earnings beat expectations - bullish outlook",
    "author": "user_6750",
    "subreddit": "investing",
    "score": 1221,
    "num_comments": 257,
    "created_utc": 1784421328.1193738,
    "url": "https://reddit.com/r/investing/",
    "timestamp": "2026-07-19T09:10:04.119703+00:00",
    "selftext": "Demo analysis for TSLA. This is fallback data - click to visit r/investing.",
    "upvote_ratio": 0.9342185678643995,
    "over_18": false,
    "stickied": false,
    "comments": 215
  },
  {
    "id": "nojlwsj",
    "title": "AMC earnings beat expectations - bullish outlook",
    "author": "user_7773",
    "subreddit": "stocks",
    "score": 1220,
    "num_comments": 126,
    "created_utc": 1784433096.1193738,
    "url": "https://reddit.com/r/stocks/",
    "timestamp": "2026-07-19T09:10:04.119876+00:00",
    "selftext": "Demo analysis for AMC. This is fallback data - click to visit r/stocks.",
    "upvote_ratio": 0.9350084141233598,
    "over_18": false,
    "stickied": false,
    "comments": 126
  },
  {
    "id": "4rzjagt",
    "title": "META earnings beat expectations - bullish outlook",
    "author": "user_6710",
    "subreddit": "investing",
    "score": 1186,
    "num_comments": 90,
    "created_utc": 1784425148.1193738,
    "url": "https://reddit.com/r/investing/",
    "timestamp": "2026-07-19T09:10:04.119651+00:00",
    "selftext": "Demo analysis for META. This is fallback data - click to visit r/investing.",
    "upvote_ratio": 0.7860907298238157,
    "over_18": false,
    "stickied": false,
    "comments": 170
  },
  {
    "id": "hswefzq",
    "title": "AMZN short squeeze potential?",
    "author": "user_3942",
    "subreddit": "investing",
    "score": 1109,
    "num_comments": 34,
    "created_utc": 1784412707.1193738,
    "url": "https://reddit.com/r/investing/",
    "timestamp": "2026-07-19T09:10:04.119775+00:00",
    "selftext": "Demo analysis for AMZN. This is fallback data - click to visit r/investing.",
    "upvote_ratio": 0.924618028333976,
    "over_18": false,
    "stickied": false,
    "comments": 89
  },
  {
    "id": "1ftlrfc",
    "title": "AMZN short squeeze potential?",
    "author": "user_7332",
    "subreddit": "investing",
    "score": 1041,
    "num_comments": 82,
    "created_utc": 1784444653.1193738,
    "url": "https://reddit.com/r/investing/",
    "timestamp": "2026-07-19T09:10:04.119482+00:00",
    "selftext": "Demo analysis for AMZN. This is fallback data - click to visit r/investing.",
    "upvote_ratio": 0.8464052720592028,
    "over_18": false,
    "stickied": false,
    "comments": 292
  },
  {
    "id": "beu74h3",
    "title": "Hold or sell TSLA? Need advice",
    "author": "user_7837",
    "subreddit": "wallstreetbets",
    "score": 902,
    "num_comments": 249,
    "created_utc": 1784418143.1193738,
    "url": "https://reddit.com/r/wallstreetbets/",
    "timestamp": "2026-07-19T09:10:04.119843+00:00",
    "selftext": "Demo analysis for TSLA. This is fallback data - click to visit r/wallstreetbets.",
    "upvote_ratio": 0.9071543828273889,
    "over_18": false,
    "stickied": false,
    "comments": 155
  },
  {
    "id": "7ojr2t3",
    "title": "AMZN news catalyst could spark rally",
    "author": "user_7574",
    "subreddit": "investing",
    "score": 854,
    "num_comments": 259,
    "created_utc": 1784410591.1193738,
    "url": "https://reddit.com/r/investing/",
    "timestamp": "2026-07-19T09:10:04.119808+00:00",
    "selftext": "Demo analysis for AMZN. This is fallback data - click to visit r/investing.",
    "upvote_ratio": 0.8813439939082546,
    "over_18": false,
    "stickied": false,
    "comments": 114
  },
  {
    "id": "m3vxiub",
    "title": "Why MSFT is the play of the decade",
    "author": "user_5390",
    "subreddit": "wallstreetbets",
    "score": 770,
    "num_comments": 270,
    "created_utc": 1784409017.1193738,
    "url": "https://reddit.com/r/wallstreetbets/",
    "timestamp": "2026-07-19T09:10:04.119668+00:00",
    "selftext": "Demo analysis for MSFT. This is fallback data - click to visit r/wallstreetbets.",
    "upvote_ratio": 0.8942897584763253,
    "over_18": false,
    "stickied": false,
    "comments": 90
  },
  {
    "id": "2vhdlzs",
    "title": "Bought 1000 shares of GOOGL - YOLO",
    "author": "user_5092",
    "subreddit": "stocks",
    "score": 639,
    "num_comments": 51,
    "created_utc": 1784413495.1193738,
    "url": "https://reddit.com/r/stocks/",
    "timestamp": "2026-07-19T09:10:04.119504+00:00",
    "selftext": "Demo analysis for GOOGL. This is fallback data - click to visit r/stocks.",
    "upvote_ratio": 0.883731149171231,
    "over_18": false,
    "stickied": false,
    "comments": 235
  },
  {
    "id": "xv3e0ox",
    "title": "NVDA news catalyst could spark rally",
    "author": "user_2068",
    "subreddit": "stocks",
    "score": 242,
    "num_comments": 272,
    "created_utc": 1784415851.1193738,
    "url": "https://reddit.com/r/stocks/",
    "timestamp": "2026-07-19T09:10:04.119825+00:00",
    "selftext": "Demo analysis for NVDA. This is fallback data - click to visit r/stocks.",
    "upvote_ratio": 0.7568637102834996,
    "over_18": false,
    "stickied": false,
    "comments": 128
  },
  {
    "id": "ezvot01",
    "title": "AMZN earnings beat expectations - bullish outlook",
    "author": "user_3001",
    "subreddit": "investing",
    "score": 96,
    "num_comments": 222,
    "created_utc": 1784432600.1193738,
    "url": "https://reddit.com/r/investing/",
    "timestamp": "2026-07-19T09:10:04.119423+00:00",
    "selftext": "Demo analysis for AMZN. This is fallback data - click to visit r/investing.",
    "upvote_ratio": 0.9056431706147483,
    "over_18": false,
    "stickied": false,
    "comments": 21
  }
]