[
  {
    "id": "72fdjrg",
    "title": "Bought 1000 shares of GME - YOLO",
    "author": "user_6611",
    "subreddit": "stocks",
    "score": 2482,
    "num_comments": 182,
    "created_utc": 1763267617.6327667,
    "url": "https://reddit.com/r/stocks/",
    "timestamp": "2025-11-16T08:32:54.633063+00:00",
    "selftext": "Demo analysis for GME. This is fallback data - click to visit r/stocks.",
    "upvote_ratio": 0.9160794870930777,
    "over_18": false,
    "stickied": false,
    "comments": 275
  },
  {
    "id": "w2xgjx9",
    "title": "Hold or sell NVDA? Need advice",
    "author": "user_3113",
    "subreddit": "investing",
    "score": 2398,
    "num_comments": 56,
    "created_utc": 1763242603.6327667,
    "url": "https://reddit.com/r/investing/",
    "timestamp": "2025-11-16T08:32:54.633074+00:00",
    "selftext": "Demo analysis for NVDA. This is fallback data - click to visit r/investing.",
    "upvote_ratio": 0.7095405285131,
    "over_18": false,
    "stickied": false,
    "comments": 240
  },
  {
    "id": "92dzz0j",
    "title": "My GME position is printing \ud83d\udcb0",
    "author": "user_6825",
    "subreddit": "stocks",
    "score": 2373,
    "num_comments": 270,
    "created_utc": 1763271584.6327667,
    "url": "https://reddit.com/r/stocks/",
    "timestamp": "2025-11-16T08:32:54.632943+00:00",
    "selftext": "Demo analysis for GME. This is fallback data - click to visit r/stocks.",
    "upvote_ratio": 0.7760559701243424,
    "over_18": false,
    "stickied": false,
    "comments": 94
  },
  {
    "id": "m5dg91d",
    "title": "META news catalyst could spark rally",
    "author": "user_9479",
    "subreddit": "stocks",
    "score": 2320,
    "num_comments": 109,
    "created_utc": 1763248166.6327667,
    "url": "https://reddit.com/r/stocks/",
    "timestamp": "2025-11-16T08:32:54.633096+00:00",
    "selftext": "Demo analysis for META. This is fallback data - click to visit r/stocks.",
    "upvote_ratio": 0.9235250222909869,
    "over_18": false,
    "stickied": false,
    "comments": 285
  },
  {
    "id": "mp6rv0x",
    "title": "Hold or sell TSLA? Need advice",
    "author": "user_4620",
    "subreddit": "investing",
    "score": 2251,
    "num_comments": 28,
    "created_utc": 1763274019.6327667,
    "url": "https://reddit.com/r/investing/",
    "timestamp": "2025-11-16T08:32:54.633085+00:00",
    "selftext": "Demo analysis for TSLA. This is fallback data - click to visit r/investing.",
    "upvote_ratio": 0.8932655749825144,
    "over_18": false,
    "stickied": false,
    "comments": 42
  },
  {
    "id": "b19epwk",
    "title": "AMC dip - perfect entry point?",
    "author": "user_3530",
    "subreddit": "investing",
    "score": 2223,
    "num_comments": 154,
    "created_utc": 1763263646.6327667,
    "url": "https://reddit.com/r/investing/",
    "timestamp": "2025-11-16T08:32:54.633031+00:00",
    "selftext": "Demo analysis for AMC. This is fallback data - click to visit r/investing.",
    "upvote_ratio": 0.7050600960337872,
    "over_18": false,
    "stickied": false,
    "comments": 150
  },
  {
    "id": "76c5ogh",
    "title": "My TSLA position is printing \ud83d\udcb0",
    "author": "user_2268",
    "subreddit": "investing",
    "score": 2057,
    "num_comments": 29,
    "created_utc": 1763252280.6327667,
    "url": "https://reddit.com/r/investing/",
    "timestamp": "2025-11-16T08:32:54.632978+00:00",
    "selftext": "Demo analysis for TSLA. This is fallback data - click to visit r/investing.",
    "upvote_ratio": 0.791964269204182,
    "over_18": false,
    "stickied": false,
    "comments": 65
  },
  {
    "id": "e98wv5i",
    "title": "My MSFT position is printing \ud83d\udcb0",
    "author": "user_1369",
    "subreddit": "wallstreetbets",
    "score": 1946,
    "num_comments": 147,
    "created_utc": 1763276676.6327667,
    "url": "https://reddit.com/r/wallstreetbets/",
    "timestamp": "2025-11-16T08:32:54.632956+00:00",
    "selftext": "Demo analysis for MSFT. This is fallback data - click to visit r/wallstreetbets.",
    "upvote_ratio": 0.8902184261780934,
    "over_18": false,
    "stickied": false,
    "comments": 253
  },
  {
    "id": "he7p9q7",
    "title": "Hold or sell NVDA? Need advice",
    "author": "user_3220",
    "subreddit": "stocks",
    "score": 1866,
    "num_comments": 209,
    "created_utc": 1763240116.6327667,
    "url": "https://reddit.com/r/stocks/",
    "timestamp": "2025-11-16T08:32:54.632999+00:00",
    "selftext": "Demo analysis for NVDA. This is fallback data - click to visit r/stocks.",
    "upvote_ratio": 0.7892572302849747,
    "over_18": false,
    "stickied": false,
    "comments": 39
  },
  {
    "id": "g5y9qzu",
    "title": "AAPL news catalyst could spark rally",
    "author": "user_4388",
    "subreddit": "stocks",
    "score": 1795,
    "num_comments": 284,
    "created_utc": 1763273448.6327667,
    "url": "https://reddit.com/r/stocks/",
    "timestamp": "2025-11-16T08:32:54.632919+00:00",
    "selftext": "Demo analysis for AAPL. This is fallback data - click to visit r/stocks.",
    "upvote_ratio": 0.8495969426159382,
    "over_18": false,
    "stickied": false,
    "comments": 40
  },
  {
    "id": "5r6lpxp",
    "title": "Bought 1000 shares of AAPL - YOLO",
    "author": "user_8606",
    "subreddit": "investing",
    "score": 1424,
    "num_comments": 61,
    "created_utc": 1763249273.6327667,
    "url": "https://reddit.com/r/investing/",
    "timestamp": "2025-11-16T08:32:54.632967+00:00",
    "selftext": "Demo analysis for AAPL. This is fallback data - click to visit r/investing.",
    "upvote_ratio": 0.7485480172697467,
    "over_18": false,
    "stickied": false,
    "comments": 65
  },
  {
    "id": "vfchex8",
    "title": "MSFT dip - perfect entry point?",
    "author": "user_7385",
    "subreddit": "stocks",
    "score": 1151,
    "num_comments": 217,
    "created_utc": 1763271693.6327667,
    "url": "https://reddit.com/r/stocks/",
    "timestamp": "2025-11-16T08:32:54.632880+00:00",
    "selftext": "Demo analysis for MSFT. This is fallback data - click to visit r/stocks.",
    "upvote_ratio": 0.8837666016849368,
    "over_18": false,
    "stickied": false,
    "comments": 45
  },
  {
    "id": "t6lssfq",
    "title": "Hold or sell META? Need advice",
    "author": "user_9834",
    "subreddit": "investing",
    "score": 1144,
    "num_comments": 57,
    "created_utc": 1763271564.6327667,
    "url": "https://reddit.com/r/investing/",
    "timestamp": "2025-11-16T08:32:54.633107+00:00",
    "selftext": "Demo analysis for META. This is fallback data - click to visit r/investing.",
    "upvote_ratio": 0.764796382613336,
    "over_18": false,
    "stickied": false,
    "comments": 216
  },
  {
    "id": "td81drp",
    "title": "NVDA short squeeze potential?",
    "author": "user_2249",
    "subreddit": "investing",
    "score": 1090,
    "num_comments": 201,
    "created_utc": 1763279062.6327667,
    "url": "https://reddit.com/r/investing/",
    "timestamp": "2025-11-16T08:32:54.632988+00:00",
    "selftext": "Demo analysis for NVDA. This is fallback data - click to visit r/investing.",
    "upvote_ratio": 0.8035602251139893,
    "over_18": false,
    "stickied": false,
    "comments": 227
  },
  {
    "id": "x5l3ex3",
    "title": "META earnings beat expectations - bullish outlook",
    "author": "user_2102",
    "subreddit": "stocks",
    "score": 1079,
    "num_comments": 247,
    "created_utc": 1763245590.6327667,
    "url": "https://reddit.com/r/stocks/",
    "timestamp": "2025-11-16T08:32:54.633010+00:00",
    "selftext": "Demo analysis for META. This is fallback data - click to visit r/stocks.",
    "upvote_ratio": 0.7863821779176856,
    "over_18": false,
    "stickied": false,
    "comments": 63
  },
  {
    "id": "2kd3k5x",
    "title": "\ud83d\ude80 GME to the moon! DD inside",
    "author": "user_1471",
    "subreddit": "wallstreetbets",
    "score": 943,
    "num_comments": 51,
    "created_utc": 1763270088.6327667,
    "url": "https://reddit.com/r/wallstreetbets/",
    "timestamp": "2025-11-16T08:32:54.632895+00:00",
    "selftext": "Demo analysis for GME. This is fallback data - click to visit r/wallstreetbets.",
    "upvote_ratio": 0.8624563061298791,
    "over_18": false,
    "stickied": false,
    "comments": 153
  },
  {
    "id": "cskz9sg",
    "title": "\ud83d\ude80 MSFT to the moon! DD inside",
    "author": "user_6732",
    "subreddit": "wallstreetbets",
    "score": 731,
    "num_comments": 73,
    "created_utc": 1763277038.6327667,
    "url": "https://reddit.com/r/wallstreetbets/",
    "timestamp": "2025-11-16T08:32:54.632854+00:00",
    "selftext": "Demo analysis for MSFT. This is fallback data - click to visit r/wallstreetbets.",
    "upvote_ratio": 0.79952306904098,
    "over_18": false,
    "stickied": false,
    "comments": 272
  },
  {
    "id": "lav4ja8",
    "title": "Technical analysis: TSLA breakout incoming",
    "author": "user_9673",
    "subreddit": "investing",
    "score": 717,
    "num_comments": 203,
    "created_utc": 1763265647.6327667,
    "url": "https://reddit.com/r/investing/",
    "timestamp": "2025-11-16T08:32:54.632809+00:00",
    "selftext": "Demo analysis for TSLA. This is fallback data - click to visit r/investing.",
    "upvote_ratio": 0.7745303168444226,
    "over_18": false,
    "stickied": false,
    "comments": 98
  },
  {
    "id": "ad28nxi",
    "title": "Technical analysis: META breakout incoming",
    "author": "user_3689",
    "subreddit": "wallstreetbets",
    "score": 706,
    "num_comments": 138,
    "created_utc": 1763265420.6327667,
    "url": "https://reddit.com/r/wallstreetbets/",
    "timestamp": "2025-11-16T08:32:54.633118+00:00",
    "selftext": "Demo analysis for META. This is fallback data - click to visit r/wallstreetbets.",
    "upvote_ratio": 0.8711702715888268,
    "over_18": false,
    "stickied": false,
    "comments": 172
  },
  {
    "id": "3jjmway",
    "title": "Hold or sell AMC? Need advice",
    "author": "user_4873",
    "subreddit": "wallstreetbets",
    "score": 705,
    "num_comments": 155,
    "created_utc": 1763264847.6327667,
    "url": "https://reddit.com/r/wallstreetbets/",
    "timestamp": "2025-11-16T08:32:54.633143+00:00",
    "selftext": "Demo analysis for AMC. This is fallback data - click to visit r/wallstreetbets.",
    "upvote_ratio": 0.7805534597520674,
    "over_18": false,
    "stickied": false,
    "comments": 94
  },
  {
    "id": "mt4aws5",
    "title": "AMC short squeeze potential?",
    "author": "user_9036",
    "subreddit": "stocks",
    "score": 674,
    "num_comments": 200,
    "created_utc": 1763280253.6327667,
    "url": "https://reddit.com/r/stocks/",
    "timestamp": "2025-11-16T08:32:54.633042+00:00",
    "selftext": "Demo analysis for AMC. This is fallback data - click to visit r/stocks.",
    "upvote_ratio": 0.7523069696102833,
    "over_18": false,
    "stickied": false,
    "comments": 68
  },
  {
    "id": "0y6jyrk",
    "title": "MSFT dip - perfect entry point?",
    "author": "user_8804",
    "subreddit": "stocks",
    "score": 565,
    "num_comments": 300,
    "created_utc": 1763250325.6327667,
    "url": "https://reddit.com/r/stocks/",
    "timestamp": "2025-11-16T08:32:54.633020+00:00",
    "selftext": "Demo analysis for MSFT. This is fallback data - click to visit r/stocks.",
    "upvote_ratio": 0.8694604000148114,
    "over_18": false,
    "stickied": false,
    "comments": 46
  },
  {
    "id": "5sd2lma",
    "title": "MSFT news catalyst could spark rally",
    "author": "user_5433",
    "subreddit": "investing",
    "score": 453,
    "num_comments": 225,
    "created_utc": 1763281705.6327667,
    "url": "https://reddit.com/r/investing/",
    "timestamp": "2025-11-16T08:32:54.632931+00:00",
    "selftext": "Demo analysis for MSFT. This is fallback data - click to visit r/investing.",
    "upvote_ratio": 0.8196760289336833,
    "over_18": false,
    "stickied": false,
    "comments": 127
  },
  {
    "id": "8855vm4",
    "title": "Why AMZN is the play of the decade",
    "author": "user_8148",
    "subreddit": "stocks",
    "score": 308,
    "num_comments": 74,
    "created_utc": 1763251373.6327667,
    "url": "https://reddit.com/r/stocks/",
    "timestamp": "2025-11-16T08:32:54.632907+00:00",
    "selftext": "Demo analysis for AMZN. This is fallback data - click to visit r/stocks.",
    "upvote_ratio": 0.8496747967231393,
    "over_18": false,
    "stickied": false,
    "comments": 264
  },
  {
    "id": "z9l448i",
    "title": "MSFT earnings beat expectations - bullish outlook",
    "author": "user_4773",
    "subreddit": "investing",
    "score": 83,
    "num_comments": 205,
    "created_utc": 1763275099.6327667,
    "url": "https://reddit.com/r/investing/",
    "timestamp": "2025-11-16T08:32:54.633053+00:00",
    "selftext": "Demo analysis for MSFT. This is fallback data - click to visit r/investing.",
    "upvote_ratio": 0.8969588828652563,
    "over_18": false,
    "stickied": false,
    "comments": 256
  }
]